LICENSE
README.md
pyproject.toml
setup.py
PyQt_SiliconUI.egg-info/PKG-INFO
PyQt_SiliconUI.egg-info/SOURCES.txt
PyQt_SiliconUI.egg-info/dependency_links.txt
PyQt_SiliconUI.egg-info/requires.txt
PyQt_SiliconUI.egg-info/top_level.txt
siui/__init__.py
siui/typing.py
siui/components/__init__.py
siui/components/button.py
siui/components/chart.py
siui/components/label.py
siui/components/slider_.py
siui/components/combobox/__init__.py
siui/components/combobox/combobox.py
siui/components/menu/__init__.py
siui/components/menu/menu.py
siui/components/menu/option.py
siui/components/menu/abstracts/__init__.py
siui/components/menu/abstracts/ani_manager.py
siui/components/menu/abstracts/menu.py
siui/components/option_card/__init__.py
siui/components/option_card/option_card.py
siui/components/option_card/abstracts/__init__.py
siui/components/option_card/abstracts/option_card.py
siui/components/page/__init__.py
siui/components/page/child_page.py
siui/components/page/page.py
siui/components/progress_bar/__init__.py
siui/components/progress_bar/progress_bar.py
siui/components/slider/__init__.py
siui/components/slider/slider.py
siui/components/spinbox/__init__.py
siui/components/spinbox/spinbox.py
siui/components/titled_widget_group/__init__.py
siui/components/titled_widget_group/titled_widget_group.py
siui/components/tooltip/__init__.py
siui/components/tooltip/tooltip.py
siui/components/widgets/__init__.py
siui/components/widgets/button.py
siui/components/widgets/container.py
siui/components/widgets/expands.py
siui/components/widgets/label.py
siui/components/widgets/line_edit.py
siui/components/widgets/navigation_bar.py
siui/components/widgets/scrollarea.py
siui/components/widgets/table.py
siui/components/widgets/timedate.py
siui/components/widgets/timeline.py
siui/components/widgets/abstracts/__init__.py
siui/components/widgets/abstracts/button.py
siui/components/widgets/abstracts/container.py
siui/components/widgets/abstracts/label.py
siui/components/widgets/abstracts/line_edit.py
siui/components/widgets/abstracts/navigation_bar.py
siui/components/widgets/abstracts/table.py
siui/components/widgets/abstracts/widget.py
siui/core/__init__.py
siui/core/alignment.py
