Metadata-Version: 2.1
Name: PyQt-SiliconUI
Version: 0.0.1
Summary: A powerful and artistic UI library based on PyQt5
Home-page: https://github.com/ChinaIceF/PyQt-SiliconUI
Author: ChinaIceF
Author-email: ChinaIceF <ChinaIceF@outlook.com>
License:                     GNU GENERAL PUBLIC LICENSE
Project-URL: Repository, https://github.com/ChinaIceF/PyQt-SiliconUI
Classifier: Development Status :: 3 - Alpha
Classifier: Intended Audience :: Developers
Classifier: Programming Language :: Python :: 3
Classifier: Programming Language :: Python :: 3.8
Classifier: Programming Language :: Python :: 3.9
Classifier: Programming Language :: Python :: 3.10
Classifier: Programming Language :: Python :: 3.11
Classifier: Programming Language :: Python :: 3.12
Classifier: Topic :: Software Development :: Libraries :: Python Modules
Requires-Python: >=3.8
License-File: LICENSE
Requires-Dist: PyQt5>=5.15.10
Requires-Dist: typing-extensions>=4.12.2
Requires-Dist: python-dateutil>=2.9.0
